[
  {
    "entityType": "flight",
    "reservationId": "1",
    "flightNumber": 1991,
    "departureDate": "8/11/2022",
    "departureTime": "8:59 PM",
    "arrivalDate": "12/4/2022",
    "arrivalTime": "5:36 PM",
    "partitionKey": "Nagbacalan",
    "destination": "Lëbushë",
    "sortKey": "Lëbushë#1991#8/11/2022"
  },
  {
    "entityType": "flight",
    "reservationId": "2",
    "flightNumber": 1633,
    "departureDate": "4/25/2022",
    "departureTime": "11:04 AM",
    "arrivalDate": "1/13/2022",
    "arrivalTime": "4:11 PM",
    "partitionKey": "Pyrgetós",
    "destination": "Kauran",
    "sortKey": "Kauran#1633#4/25/2022"
  },
  {
    "entityType": "flight",
    "reservationId": "3",
    "flightNumber": 5327,
    "departureDate": "10/6/2022",
    "departureTime": "11:27 AM",
    "arrivalDate": "2/5/2022",
    "arrivalTime": "11:51 AM",
    "partitionKey": "Dzüünharaa",
    "destination": "Nyíregyháza",
    "sortKey": "Nyíregyháza#5327#10/6/2022"
  },
  {
    "entityType": "flight",
    "reservationId": "4",
    "flightNumber": 6877,
    "departureDate": "6/13/2022",
    "departureTime": "12:13 PM",
    "arrivalDate": "5/8/2022",
    "arrivalTime": "3:07 AM",
    "partitionKey": "Ma'an",
    "destination": "Mernek",
    "sortKey": "Mernek#6877#6/13/2022"
  },
  {
    "entityType": "flight",
    "reservationId": "5",
    "flightNumber": 8243,
    "departureDate": "3/22/2022",
    "departureTime": "11:57 AM",
    "arrivalDate": "2/24/2022",
    "arrivalTime": "10:56 PM",
    "partitionKey": "Dulian",
    "destination": "Panguipulli",
    "sortKey": "Panguipulli#8243#3/22/2022"
  },
  {
    "entityType": "flight",
    "reservationId": "6",
    "flightNumber": 6318,
    "departureDate": "4/4/2022",
    "departureTime": "10:54 PM",
    "arrivalDate": "11/7/2022",
    "arrivalTime": "1:53 AM",
    "partitionKey": "Wiset Chaichan",
    "destination": "Seynod",
    "sortKey": "Seynod#6318#4/4/2022"
  },
  {
    "entityType": "flight",
    "reservationId": "7",
    "flightNumber": 9255,
    "departureDate": "7/14/2022",
    "departureTime": "1:01 PM",
    "arrivalDate": "6/27/2022",
    "arrivalTime": "7:00 PM",
    "partitionKey": "Faisalābād",
    "destination": "Dolní Čermná",
    "sortKey": "Dolní Čermná#9255#7/14/2022"
  },
  {
    "entityType": "flight",
    "reservationId": "8",
    "flightNumber": 6021,
    "departureDate": "5/13/2022",
    "departureTime": "1:41 AM",
    "arrivalDate": "3/6/2022",
    "arrivalTime": "11:57 PM",
    "partitionKey": "Malasila",
    "destination": "Jinxiang",
    "sortKey": "Jinxiang#6021#5/13/2022"
  },
  {
    "entityType": "flight",
    "reservationId": "9",
    "flightNumber": 1228,
    "departureDate": "8/9/2022",
    "departureTime": "9:45 PM",
    "arrivalDate": "8/28/2022",
    "arrivalTime": "12:07 PM",
    "partitionKey": "Port Saint Lucie",
    "destination": "Newark",
    "sortKey": "Newark#1228#8/9/2022"
  },
  {
    "entityType": "flight",
    "reservationId": "10",
    "flightNumber": 7540,
    "departureDate": "1/10/2022",
    "departureTime": "5:39 AM",
    "arrivalDate": "7/10/2022",
    "arrivalTime": "10:38 PM",
    "partitionKey": "Tianyuan",
    "destination": "Nevesinje",
    "sortKey": "Nevesinje#7540#1/10/2022"
  },
  {
    "entityType": "flight",
    "reservationId": "11",
    "flightNumber": 3617,
    "departureDate": "2/9/2022",
    "departureTime": "7:21 PM",
    "arrivalDate": "11/27/2022",
    "arrivalTime": "12:47 AM",
    "partitionKey": "Guzhan",
    "destination": "Parenggan",
    "sortKey": "Parenggan#3617#2/9/2022"
  },
  {
    "entityType": "flight",
    "reservationId": "12",
    "flightNumber": 4380,
    "departureDate": "4/2/2022",
    "departureTime": "5:52 AM",
    "arrivalDate": "5/24/2022",
    "arrivalTime": "4:57 PM",
    "partitionKey": "Tintina",
    "destination": "Philadelphia",
    "sortKey": "Philadelphia#4380#4/2/2022"
  },
  {
    "entityType": "flight",
    "reservationId": "13",
    "flightNumber": 9061,
    "departureDate": "10/27/2022",
    "departureTime": "1:17 PM",
    "arrivalDate": "9/5/2022",
    "arrivalTime": "5:10 AM",
    "partitionKey": "Soi Dao",
    "destination": "Eldoret",
    "sortKey": "Eldoret#9061#10/27/2022"
  },
  {
    "entityType": "flight",
    "reservationId": "14",
    "flightNumber": 8491,
    "departureDate": "8/5/2022",
    "departureTime": "4:07 AM",
    "arrivalDate": "12/16/2022",
    "arrivalTime": "10:24 PM",
    "partitionKey": "Gudong",
    "destination": "Orurillo",
    "sortKey": "Orurillo#8491#8/5/2022"
  },
  {
    "entityType": "flight",
    "reservationId": "15",
    "flightNumber": 1140,
    "departureDate": "12/29/2022",
    "departureTime": "8:57 PM",
    "arrivalDate": "8/25/2022",
    "arrivalTime": "11:18 PM",
    "partitionKey": "Esperanza",
    "destination": "Lian",
    "sortKey": "Lian#1140#12/29/2022"
  },
  {
    "entityType": "flight",
    "reservationId": "16",
    "flightNumber": 4526,
    "departureDate": "6/1/2022",
    "departureTime": "3:57 AM",
    "arrivalDate": "2/24/2022",
    "arrivalTime": "9:52 PM",
    "partitionKey": "Gorbatov",
    "destination": "Benito Juarez",
    "sortKey": "Benito Juarez#4526#6/1/2022"
  },
  {
    "entityType": "flight",
    "reservationId": "17",
    "flightNumber": 2876,
    "departureDate": "8/27/2022",
    "departureTime": "7:32 AM",
    "arrivalDate": "8/23/2022",
    "arrivalTime": "4:44 PM",
    "partitionKey": "Tianzhu",
    "destination": "Voždovac",
    "sortKey": "Voždovac#2876#8/27/2022"
  },
  {
    "entityType": "flight",
    "reservationId": "18",
    "flightNumber": 2337,
    "departureDate": "10/29/2022",
    "departureTime": "6:53 AM",
    "arrivalDate": "1/20/2022",
    "arrivalTime": "5:03 AM",
    "partitionKey": "Melaka",
    "destination": "Āshtīān",
    "sortKey": "Āshtīān#2337#10/29/2022"
  },
  {
    "entityType": "flight",
    "reservationId": "19",
    "flightNumber": 6646,
    "departureDate": "2/20/2022",
    "departureTime": "4:29 AM",
    "arrivalDate": "1/18/2022",
    "arrivalTime": "2:15 PM",
    "partitionKey": "Medianeira",
    "destination": "Lestijärvi",
    "sortKey": "Lestijärvi#6646#2/20/2022"
  },
  {
    "entityType": "flight",
    "reservationId": "20",
    "flightNumber": 6460,
    "departureDate": "12/5/2022",
    "departureTime": "12:13 AM",
    "arrivalDate": "7/11/2022",
    "arrivalTime": "10:01 AM",
    "partitionKey": "Ústí nad Orlicí",
    "destination": "Fucheng",
    "sortKey": "Fucheng#6460#12/5/2022"
  },
  {
    "entityType": "flight",
    "reservationId": "21",
    "flightNumber": 1712,
    "departureDate": "10/24/2022",
    "departureTime": "2:04 AM",
    "arrivalDate": "3/14/2022",
    "arrivalTime": "4:40 AM",
    "partitionKey": "Xijiang",
    "destination": "Piastów",
    "sortKey": "Piastów#1712#10/24/2022"
  },
  {
    "entityType": "flight",
    "reservationId": "22",
    "flightNumber": 3248,
    "departureDate": "8/22/2022",
    "departureTime": "4:11 PM",
    "arrivalDate": "1/18/2022",
    "arrivalTime": "12:43 PM",
    "partitionKey": "Dadiya",
    "destination": "Tan Sum",
    "sortKey": "Tan Sum#3248#8/22/2022"
  },
  {
    "entityType": "flight",
    "reservationId": "23",
    "flightNumber": 3876,
    "departureDate": "6/12/2022",
    "departureTime": "5:49 PM",
    "arrivalDate": "10/18/2022",
    "arrivalTime": "10:53 PM",
    "partitionKey": "Bettendorf",
    "destination": "Wlingi",
    "sortKey": "Wlingi#3876#6/12/2022"
  },
  {
    "entityType": "flight",
    "reservationId": "24",
    "flightNumber": 2636,
    "departureDate": "11/17/2022",
    "departureTime": "12:30 AM",
    "arrivalDate": "11/14/2022",
    "arrivalTime": "10:12 PM",
    "partitionKey": "Jiaozhou",
    "destination": "Doug An",
    "sortKey": "Doug An#2636#11/17/2022"
  },
  {
    "entityType": "flight",
    "reservationId": "25",
    "flightNumber": 7044,
    "departureDate": "6/25/2022",
    "departureTime": "7:55 PM",
    "arrivalDate": "6/29/2022",
    "arrivalTime": "6:59 PM",
    "partitionKey": "Şafāshahr",
    "destination": "Keboncau",
    "sortKey": "Keboncau#7044#6/25/2022"
  },
  {
    "entityType": "flight",
    "reservationId": "26",
    "flightNumber": 5947,
    "departureDate": "1/11/2022",
    "departureTime": "2:38 AM",
    "arrivalDate": "8/21/2022",
    "arrivalTime": "12:41 AM",
    "partitionKey": "Caraga",
    "destination": "Jargalant",
    "sortKey": "Jargalant#5947#1/11/2022"
  },
  {
    "entityType": "flight",
    "reservationId": "27",
    "flightNumber": 9325,
    "departureDate": "1/27/2022",
    "departureTime": "3:39 AM",
    "arrivalDate": "10/23/2022",
    "arrivalTime": "2:05 AM",
    "partitionKey": "Nglengkir",
    "destination": "Qingyang",
    "sortKey": "Qingyang#9325#1/27/2022"
  },
  {
    "entityType": "flight",
    "reservationId": "28",
    "flightNumber": 5186,
    "departureDate": "11/16/2022",
    "departureTime": "4:11 PM",
    "arrivalDate": "1/19/2022",
    "arrivalTime": "2:29 AM",
    "partitionKey": "Lugo",
    "destination": "Kim Sơn",
    "sortKey": "Kim Sơn#5186#11/16/2022"
  },
  {
    "entityType": "flight",
    "reservationId": "29",
    "flightNumber": 9978,
    "departureDate": "9/14/2022",
    "departureTime": "11:03 PM",
    "arrivalDate": "2/21/2022",
    "arrivalTime": "7:23 AM",
    "partitionKey": "Mashiko",
    "destination": "Wenquan",
    "sortKey": "Wenquan#9978#9/14/2022"
  },
  {
    "entityType": "flight",
    "reservationId": "30",
    "flightNumber": 5322,
    "departureDate": "12/5/2022",
    "departureTime": "8:40 AM",
    "arrivalDate": "11/22/2022",
    "arrivalTime": "12:07 PM",
    "partitionKey": "Diyarb Najm",
    "destination": "Punsu",
    "sortKey": "Punsu#5322#12/5/2022"
  },
  {
    "entityType": "flight",
    "reservationId": "31",
    "flightNumber": 4208,
    "departureDate": "10/1/2022",
    "departureTime": "9:36 AM",
    "arrivalDate": "3/30/2022",
    "arrivalTime": "3:36 AM",
    "partitionKey": "Mirovice",
    "destination": "Ananea",
    "sortKey": "Ananea#4208#10/1/2022"
  },
  {
    "entityType": "flight",
    "reservationId": "32",
    "flightNumber": 1604,
    "departureDate": "6/6/2022",
    "departureTime": "6:02 PM",
    "arrivalDate": "9/29/2022",
    "arrivalTime": "8:29 PM",
    "partitionKey": "Qala i Naw",
    "destination": "Bolszewo",
    "sortKey": "Bolszewo#1604#6/6/2022"
  },
  {
    "entityType": "flight",
    "reservationId": "33",
    "flightNumber": 9533,
    "departureDate": "2/11/2022",
    "departureTime": "2:04 AM",
    "arrivalDate": "11/21/2022",
    "arrivalTime": "9:39 PM",
    "partitionKey": "Jinkou",
    "destination": "Vrýses",
    "sortKey": "Vrýses#9533#2/11/2022"
  },
  {
    "entityType": "flight",
    "reservationId": "34",
    "flightNumber": 8044,
    "departureDate": "2/13/2022",
    "departureTime": "1:53 PM",
    "arrivalDate": "10/22/2022",
    "arrivalTime": "5:45 AM",
    "partitionKey": "Zhongzi",
    "destination": "Chernomorets",
    "sortKey": "Chernomorets#8044#2/13/2022"
  },
  {
    "entityType": "flight",
    "reservationId": "35",
    "flightNumber": 9280,
    "departureDate": "6/18/2022",
    "departureTime": "1:45 PM",
    "arrivalDate": "7/19/2022",
    "arrivalTime": "5:50 PM",
    "partitionKey": "Jiachuan",
    "destination": "Srabah",
    "sortKey": "Srabah#9280#6/18/2022"
  },
  {
    "entityType": "flight",
    "reservationId": "36",
    "flightNumber": 6157,
    "departureDate": "4/15/2022",
    "departureTime": "11:49 AM",
    "arrivalDate": "7/18/2022",
    "arrivalTime": "11:22 AM",
    "partitionKey": "El Calvario",
    "destination": "Zhuanshui",
    "sortKey": "Zhuanshui#6157#4/15/2022"
  },
  {
    "entityType": "flight",
    "reservationId": "37",
    "flightNumber": 3311,
    "departureDate": "3/28/2022",
    "departureTime": "9:11 AM",
    "arrivalDate": "5/6/2022",
    "arrivalTime": "9:08 PM",
    "partitionKey": "Bojonegoro",
    "destination": "Sukowidodo Barat",
    "sortKey": "Sukowidodo Barat#3311#3/28/2022"
  },
  {
    "entityType": "flight",
    "reservationId": "38",
    "flightNumber": 9367,
    "departureDate": "4/4/2022",
    "departureTime": "9:54 PM",
    "arrivalDate": "11/9/2022",
    "arrivalTime": "12:35 PM",
    "partitionKey": "Tosno",
    "destination": "Bizhou",
    "sortKey": "Bizhou#9367#4/4/2022"
  },
  {
    "entityType": "flight",
    "reservationId": "39",
    "flightNumber": 5397,
    "departureDate": "10/8/2022",
    "departureTime": "6:14 AM",
    "arrivalDate": "5/5/2022",
    "arrivalTime": "4:11 PM",
    "partitionKey": "Miaoyu",
    "destination": "Santa Anita",
    "sortKey": "Santa Anita#5397#10/8/2022"
  },
  {
    "entityType": "flight",
    "reservationId": "40",
    "flightNumber": 2561,
    "departureDate": "9/9/2022",
    "departureTime": "11:21 PM",
    "arrivalDate": "1/9/2022",
    "arrivalTime": "3:50 PM",
    "partitionKey": "Pak Kret",
    "destination": "Ituverava",
    "sortKey": "Ituverava#2561#9/9/2022"
  },
  {
    "entityType": "flight",
    "reservationId": "41",
    "flightNumber": 3127,
    "departureDate": "7/16/2022",
    "departureTime": "1:41 PM",
    "arrivalDate": "8/4/2022",
    "arrivalTime": "3:29 AM",
    "partitionKey": "Oro Timur",
    "destination": "Cabricán",
    "sortKey": "Cabricán#3127#7/16/2022"
  },
  {
    "entityType": "flight",
    "reservationId": "42",
    "flightNumber": 4008,
    "departureDate": "11/1/2022",
    "departureTime": "11:07 AM",
    "arrivalDate": "4/27/2022",
    "arrivalTime": "3:45 PM",
    "partitionKey": "Jambuir Timur",
    "destination": "Bettendorf",
    "sortKey": "Bettendorf#4008#11/1/2022"
  },
  {
    "entityType": "flight",
    "reservationId": "43",
    "flightNumber": 6382,
    "departureDate": "4/10/2022",
    "departureTime": "4:13 AM",
    "arrivalDate": "2/7/2022",
    "arrivalTime": "3:22 PM",
    "partitionKey": "Valdivia",
    "destination": "Meishan",
    "sortKey": "Meishan#6382#4/10/2022"
  },
  {
    "entityType": "flight",
    "reservationId": "44",
    "flightNumber": 4633,
    "departureDate": "10/19/2022",
    "departureTime": "2:57 PM",
    "arrivalDate": "8/18/2022",
    "arrivalTime": "6:04 AM",
    "partitionKey": "Serere",
    "destination": "Kongoussi",
    "sortKey": "Kongoussi#4633#10/19/2022"
  },
  {
    "entityType": "flight",
    "reservationId": "45",
    "flightNumber": 8019,
    "departureDate": "6/13/2022",
    "departureTime": "7:37 PM",
    "arrivalDate": "7/20/2022",
    "arrivalTime": "9:49 PM",
    "partitionKey": "Vale Mourão",
    "destination": "Rudky",
    "sortKey": "Rudky#8019#6/13/2022"
  },
  {
    "entityType": "flight",
    "reservationId": "46",
    "flightNumber": 5935,
    "departureDate": "7/7/2022",
    "departureTime": "4:20 AM",
    "arrivalDate": "7/27/2022",
    "arrivalTime": "6:34 PM",
    "partitionKey": "Nguigmi",
    "destination": "Fargo",
    "sortKey": "Fargo#5935#7/7/2022"
  },
  {
    "entityType": "flight",
    "reservationId": "47",
    "flightNumber": 7235,
    "departureDate": "10/18/2022",
    "departureTime": "4:35 PM",
    "arrivalDate": "5/26/2022",
    "arrivalTime": "6:33 PM",
    "partitionKey": "Watuweri",
    "destination": "Takaishi",
    "sortKey": "Takaishi#7235#10/18/2022"
  },
  {
    "entityType": "flight",
    "reservationId": "48",
    "flightNumber": 8882,
    "departureDate": "7/2/2022",
    "departureTime": "7:56 PM",
    "arrivalDate": "9/15/2022",
    "arrivalTime": "5:13 AM",
    "partitionKey": "Chengzihe",
    "destination": "Séguéla",
    "sortKey": "Séguéla#8882#7/2/2022"
  },
  {
    "entityType": "flight",
    "reservationId": "49",
    "flightNumber": 2365,
    "departureDate": "4/23/2022",
    "departureTime": "9:59 PM",
    "arrivalDate": "12/22/2022",
    "arrivalTime": "10:05 AM",
    "partitionKey": "Angoulême",
    "destination": "Banja Luka",
    "sortKey": "Banja Luka#2365#4/23/2022"
  },
  {
    "entityType": "flight",
    "reservationId": "50",
    "flightNumber": 7252,
    "departureDate": "12/14/2022",
    "departureTime": "10:39 AM",
    "arrivalDate": "4/29/2022",
    "arrivalTime": "10:32 PM",
    "partitionKey": "Al Ḩashwah",
    "destination": "Nizhniy Chir",
    "sortKey": "Nizhniy Chir#7252#12/14/2022"
    }
  }
]
